people_local/__init__.py
people_local/people.py
people_local/people_constants.py
people_local-0.0.31.dist-info/METADATA
people_local-0.0.31.dist-info/WHEEL
people_local-0.0.31.dist-info/top_level.txt
people_local-0.0.31.dist-info/RECORD
