Metadata-Version: 2.1
Name: people-local
Version: 0.0.31
Summary: PyPI Package for Circles people-local Python
Home-page: https://github.com/circles-zone/people-local-python-package/
Author: Circles
Author-email: info@circlez.ai
Classifier: Programming Language :: Python :: 3
Classifier: License :: Other/Proprietary License
Classifier: Operating System :: OS Independent
Requires-Dist: database-mysql-local >=0.0.345
Requires-Dist: logger-local >=0.0.145
Requires-Dist: group-local >=0.0.30
Requires-Dist: python-sdk-remote >=0.0.109
